eigeneval/__init__.py
eigeneval-0.1.0.dist-info/METADATA
eigeneval-0.1.0.dist-info/WHEEL
eigeneval-0.1.0.dist-info/top_level.txt
eigeneval-0.1.0.dist-info/RECORD
