Metadata-Version: 2.4
Name: eigeneval
Version: 0.1.0
Summary: Evaluations!
Author-email: Andrew <andrew@wandb.com>
License: MIT
Requires-Python: >=3.7
